Scarf/Main.py
Scarf/Tip.py
Scarf/__init__.py
Scarf/paramter.py
Scarf/Base/TCPServer.py
Scarf/Base/ThreadPool.py
Scarf/Base/__init__.py
Scarf/Context/Context.py
Scarf/Context/Log.py
Scarf/Context/RequestReslove.py
Scarf/Context/Timer.py
Scarf/Context/__init__.py
Scarf/Protocol/ClientRequest.py
Scarf/Protocol/HTTP.py
Scarf/Protocol/HTTP2.py
Scarf/Protocol/WebSocket.py
Scarf/Protocol/__init__.py
ScarfKit-1.0.2.dist-info/METADATA
ScarfKit-1.0.2.dist-info/WHEEL
ScarfKit-1.0.2.dist-info/top_level.txt
ScarfKit-1.0.2.dist-info/RECORD
