Metadata-Version: 2.1
Name: ScarfKit
Version: 1.0.2
Summary: A Simple Way To Create Web Server
Home-page: https://github.com/KeepRepeatLoop/Scarf
Author: Qc
Author-email: qcsdfsdvdac@gmail.com
License: UNKNOWN
Project-URL: Bug Tracker, https://github.com/KeepRepeatLoop/Scarf/issues
Platform: UNKNOWN
Classifier: Programming Language :: Python :: 3
Classifier: License :: OSI Approved :: Apache Software License
Classifier: Operating System :: OS Independent
Requires-Python: >=3.5
